actionstreamer/__init__.py
actionstreamer/CommonFunctions/__init__.py
actionstreamer/CommonFunctions/common_functions.py
actionstreamer/CommonFunctions/Wifi/__init__.py
actionstreamer/CommonFunctions/Wifi/wifi.py
actionstreamer/Config/__init__.py
actionstreamer/Config/config.py
actionstreamer/DeviceFunctions/__init__.py
actionstreamer/DeviceFunctions/device_functions.py
actionstreamer/DeviceHealthFunctions/__init__.py
actionstreamer/DeviceHealthFunctions/device_health_functions.py
actionstreamer/Model/__init__.py
actionstreamer/Model/agent_type.py
actionstreamer/Model/camera_multiplex_args.py
actionstreamer/Model/capture_frames_args.py
actionstreamer/Model/clear_flag_queue_args.py
actionstreamer/Model/collection_base.py
actionstreamer/Model/concatenate_clips_args.py
actionstreamer/Model/conference_args.py
actionstreamer/Model/create_event_preset.py
actionstreamer/Model/create_video_clip.py
actionstreamer/Model/date_time_encoder.py
actionstreamer/Model/device.py
actionstreamer/Model/device_group.py
actionstreamer/Model/device_health.py
actionstreamer/Model/device_health_row.py
actionstreamer/Model/epoch_range.py
actionstreamer/Model/event.py
actionstreamer/Model/event_args.py
actionstreamer/Model/event_details.py
actionstreamer/Model/event_preset.py
actionstreamer/Model/event_preset_workflow_args.py
actionstreamer/Model/event_status.py
actionstreamer/Model/event_type.py
actionstreamer/Model/event_with_names.py
actionstreamer/Model/file.py
actionstreamer/Model/item_type.py
actionstreamer/Model/log_message.py
actionstreamer/Model/microphone_multiplex_args.py
actionstreamer/Model/multiplex_conference_args.py
actionstreamer/Model/multiplex_leave_conference_args.py
actionstreamer/Model/multiplex_recording_args.py
actionstreamer/Model/multiplex_stop_recording_args.py
actionstreamer/Model/name_value_pair.py
actionstreamer/Model/notification.py
actionstreamer/Model/package.py
actionstreamer/Model/patch_operation.py
actionstreamer/Model/receive_actionync_args.py
actionstreamer-1.4.5.dist-info/METADATA
actionstreamer-1.4.5.dist-info/WHEEL
actionstreamer-1.4.5.dist-info/RECORD
