Metadata-Version: 2.1
Name: actionstreamer
Version: 1.4.5
Summary: A library for the ActionStreamer API.
Author: ActionStreamer
Author-email: joe@actionstreamer.com
Requires-Python: >=3.10,<4.0
Classifier: Programming Language :: Python :: 3
Classifier: Programming Language :: Python :: 3.10
Classifier: Programming Language :: Python :: 3.11
Classifier: Programming Language :: Python :: 3.12
Requires-Dist: psutil (>=6.0.0)
Requires-Dist: pycryptodome (>=3.23.0)
Requires-Dist: pytz (>=2024.1,<2025.0)
Requires-Dist: requests (>=2.32.3,<3.0.0)
Requires-Dist: wmi (>=1.5.1,<2.0.0) ; sys_platform == "win32"
